cminpack_numba/.DS_Store
cminpack_numba/__init__.py
cminpack_numba/bounds.py
cminpack_numba/chkder.py
cminpack_numba/cminpack_.py
cminpack_numba/dpmpar.py
cminpack_numba/enorm.py
cminpack_numba/hybrd.py
cminpack_numba/hybrj.py
cminpack_numba/libcminpack.1.3.11.dylib
cminpack_numba/libcminpack.1.dylib
cminpack_numba/libcminpack.dylib
cminpack_numba/libcminpacks.1.3.11.dylib
cminpack_numba/libcminpacks.1.dylib
cminpack_numba/libcminpacks.dylib
cminpack_numba/lmder.py
cminpack_numba/lmdif.py
cminpack_numba/lmstr.py
cminpack_numba/signatures.py
cminpack_numba/utils.py
cminpack_numba/pkgconfig/cminpack.pc
cminpack_numba/pkgconfig/cminpacks.pc
include/cminpack-1/cminpack.h
include/cminpack-1/minpack.h
share/cminpack/CMinpackConfig-relwithdebinfo.cmake
share/cminpack/CMinpackConfig.cmake
cminpack_numba-0.1.4.dist-info/LICENSE
cminpack_numba-0.1.4.dist-info/METADATA
cminpack_numba-0.1.4.dist-info/WHEEL
cminpack_numba-0.1.4.dist-info/entry_points.txt
cminpack_numba-0.1.4.dist-info/RECORD
