Metadata-Version: 2.1
Name: cminpack-numba
Version: 0.1.4
Summary: A numba compatible wrapper of cminpack.
Author-Email: Chris Ninham <christopher.ninham@creatis.insa-lyon.fr>
License: MIT License
Requires-Dist: numba
Requires-Dist: numpy
Requires-Dist: pytest; extra == "tests"
Requires-Dist: pytest-benchmark; extra == "tests"
Requires-Dist: scipy; extra == "tests"
Requires-Dist: NumbaMinpack; extra == "tests"
Requires-Dist: ruff; extra == "dev"
Provides-Extra: tests
Provides-Extra: dev
